mcgt/__init__.py
mcgt/phase.py
mcgt/scalar_perturbations.py
mcgt/backends/ref_phase.py
mcgt_core-0.2.30.dist-info/licenses/LICENSE
mcgt_core-0.2.30.dist-info/METADATA
mcgt_core-0.2.30.dist-info/WHEEL
mcgt_core-0.2.30.dist-info/top_level.txt
mcgt_core-0.2.30.dist-info/RECORD
