Metadata-Version: 2.4
Name: mcgt-core
Version: 0.2.30
License-File: LICENSE
Requires-Dist: numpy>=1.25
Requires-Dist: scipy>=1.10
Dynamic: license-file
